pixelinkWrapper/__init__.py
pixelinkWrapper/pixelink.py
pixelinkwrapper-1.4.1.dist-info/licenses/LICENSE.txt
pixelinkwrapper-1.4.1.dist-info/METADATA
pixelinkwrapper-1.4.1.dist-info/WHEEL
pixelinkwrapper-1.4.1.dist-info/top_level.txt
pixelinkwrapper-1.4.1.dist-info/RECORD
