Metadata-Version: 2.4
Name: pixelinkWrapper
Version: 1.4.1
Summary: A Pixelink API Python wrapper for Pixelink cameras
Home-page: https://github.com/pixelink-support/pixelinkPythonWrapper
Author: Pixelink an Ametek company
Author-email: pixelink.support@ametek.com
Project-URL: Bug Reports, https://support.pixelink.com/support/tickets/new
Keywords: pixelink api wrapper camera application development
Classifier: Development Status :: 5 - Production/Stable
Classifier: Intended Audience :: Developers
Classifier: Topic :: Software Development
Classifier: License :: OSI Approved :: MIT License
Classifier: Natural Language :: English
Classifier: Operating System :: Microsoft :: Windows
Classifier: Operating System :: POSIX :: Linux
Classifier: Programming Language :: Python :: 3
Classifier: Topic :: Multimedia :: Graphics :: Capture :: Digital Camera
Classifier: Topic :: Multimedia :: Video :: Capture
Requires-Python: ~=3.0
License-File: LICENSE.txt
Dynamic: author
Dynamic: author-email
Dynamic: classifier
Dynamic: description
Dynamic: description-content-type
Dynamic: home-page
Dynamic: keywords
Dynamic: license-file
Dynamic: project-url
Dynamic: requires-python
Dynamic: summary
